somali_spelling_correction/Dataset_Spelling.csv
somali_spelling_correction/__init__.py
somali_spelling_correction/corrector.py
somali_spelling_correction-0.6.dist-info/METADATA
somali_spelling_correction-0.6.dist-info/WHEEL
somali_spelling_correction-0.6.dist-info/top_level.txt
somali_spelling_correction-0.6.dist-info/RECORD
