Metadata-Version: 2.2
Name: somali_spelling_correction
Version: 0.6
Summary: Somali Spelling Correction Package
Home-page: https://github.com/abdoltd/somali_spelling_correction
Author: R&D
Author-email: abdoldevtra@example.com
Dynamic: author
Dynamic: author-email
Dynamic: description
Dynamic: description-content-type
Dynamic: home-page
Dynamic: summary
